[
  {
    "x": 0.21,
    "y": 0.26,
    "intensity": 0.95
  },
  {
    "x": 0.21,
    "y": 0.32,
    "intensity": 0.85
  },
  {
    "x": 0.47,
    "y": 0.32,
    "intensity": 0.85
  },
  {
    "x": 0.72,
    "y": 0.32,
    "intensity": 0.85
  },
  {
    "x": 0.21,
    "y": 0.37,
    "intensity": 0.85
  },
  {
    "x": 0.47,
    "y": 0.37,
    "intensity": 0.85
  },
  {
    "x": 0.72,
    "y": 0.37,
    "intensity": 0.85
  },
  {
    "x": 0.21,
    "y": 0.42,
    "intensity": 0.85
  },
  {
    "x": 0.47,
    "y": 0.42,
    "intensity": 0.85
  },
  {
    "x": 0.72,
    "y": 0.42,
    "intensity": 0.85
  },
  {
    "x": 0.21,
    "y": 0.47,
    "intensity": 0.85
  },
  {
    "x": 0.47,
    "y": 0.47,
    "intensity": 0.85
  },
  {
    "x": 0.72,
    "y": 0.47,
    "intensity": 0.85
  },
  {
    "x": 0.21,
    "y": 0.52,
    "intensity": 0.85
  },
  {
    "x": 0.47,
    "y": 0.52,
    "intensity": 0.85
  },
  {
    "x": 0.72,
    "y": 0.52,
    "intensity": 0.85
  },
  {
    "x": 0.21,
    "y": 0.57,
    "intensity": 0.85
  },
  {
    "x": 0.47,
    "y": 0.57,
    "intensity": 0.85
  },
  {
    "x": 0.72,
    "y": 0.57,
    "intensity": 0.85
  },
  {
    "x": 0.21,
    "y": 0.62,
    "intensity": 0.85
  },
  {
    "x": 0.47,
    "y": 0.62,
    "intensity": 0.85
  },
  {
    "x": 0.72,
    "y": 0.62,
    "intensity": 0.85
  },
  {
    "x": 0.21,
    "y": 0.67,
    "intensity": 0.85
  },
  {
    "x": 0.47,
    "y": 0.67,
    "intensity": 0.85
  },
  {
    "x": 0.72,
    "y": 0.67,
    "intensity": 0.85
  },
  {
    "x": 0.64,
    "y": 0.71,
    "intensity": 0.9
  },
  {
    "x": 0.81,
    "y": 0.71,
    "intensity": 0.9
  },
  {
    "x": 0.47,
    "y": 0.71,
    "intensity": 0.9
  },
  {
    "x": 0.21,
    "y": 0.71,
    "intensity": 0.9
  },
  {
    "x": 0.47,
    "y": 0.26,
    "intensity": 0.95
  }
]